pysolarfrontier/__init__.py
pysolarfrontier-1.1.dist-info/LICENSE
pysolarfrontier-1.1.dist-info/METADATA
pysolarfrontier-1.1.dist-info/WHEEL
pysolarfrontier-1.1.dist-info/top_level.txt
pysolarfrontier-1.1.dist-info/RECORD
