Metadata-Version: 2.1
Name: pysolarfrontier
Version: 1.1
Summary: Library to communicate with Solar Frotier inverters
Home-page: https://github.com/coen800/pysolarfrontier
Author: coen800
License: UNKNOWN
Platform: UNKNOWN
Classifier: Programming Language :: Python :: 3
Classifier: License :: OSI Approved :: MIT License
Classifier: Operating System :: OS Independent
Requires-Python: >=3.6
